KB4IT-0.7.8.data/data/kb4it/resources/themes/default/theme.adoc
KB4IT-0.7.8.data/data/kb4it/resources/themes/default/framework/uikit/css/coderay-asciidoctor.css
KB4IT-0.7.8.data/data/kb4it/resources/themes/default/framework/uikit/css/kb4it.css
KB4IT-0.7.8.data/data/kb4it/resources/themes/default/framework/uikit/css/print.css
KB4IT-0.7.8.data/data/kb4it/resources/themes/default/framework/uikit/css/uikit-rtl.css
KB4IT-0.7.8.data/data/kb4it/resources/themes/default/framework/uikit/css/uikit-rtl.min.css
KB4IT-0.7.8.data/data/kb4it/resources/themes/default/framework/uikit/css/uikit.css
KB4IT-0.7.8.data/data/kb4it/resources/themes/default/framework/uikit/css/uikit.min.css
KB4IT-0.7.8.data/data/kb4it/resources/themes/default/framework/uikit/js/uikit-icons.js
KB4IT-0.7.8.data/data/kb4it/resources/themes/default/framework/uikit/js/uikit-icons.min.js
KB4IT-0.7.8.data/data/kb4it/resources/themes/default/framework/uikit/js/uikit.js
KB4IT-0.7.8.data/data/kb4it/resources/themes/default/framework/uikit/js/uikit.min.js
KB4IT-0.7.8.data/data/kb4it/resources/themes/default/images/logo.png
KB4IT-0.7.8.data/data/kb4it/resources/themes/default/logic/theme.py
KB4IT-0.7.8.data/data/kb4it/resources/themes/default/templates/CARD_DOC.tpl
KB4IT-0.7.8.data/data/kb4it/resources/themes/default/templates/CARD_DOC_CLASS.tpl
KB4IT-0.7.8.data/data/kb4it/resources/themes/default/templates/CARD_DOC_FILTER_DATA_TITLE.tpl
KB4IT-0.7.8.data/data/kb4it/resources/themes/default/templates/HTML_FOOTER.tpl
KB4IT-0.7.8.data/data/kb4it/resources/themes/default/templates/HTML_HEADER_COMMON.tpl
KB4IT-0.7.8.data/data/kb4it/resources/themes/default/templates/HTML_HEADER_DOC.tpl
KB4IT-0.7.8.data/data/kb4it/resources/themes/default/templates/HTML_HEADER_MENU_CONTENTS_DISABLED.tpl
KB4IT-0.7.8.data/data/kb4it/resources/themes/default/templates/HTML_HEADER_MENU_CONTENTS_ENABLED.tpl
KB4IT-0.7.8.data/data/kb4it/resources/themes/default/templates/HTML_HEADER_NODOC.tpl
KB4IT-0.7.8.dist-info/AUTHORS
KB4IT-0.7.8.dist-info/LICENSE
KB4IT-0.7.8.dist-info/METADATA
KB4IT-0.7.8.dist-info/WHEEL
KB4IT-0.7.8.dist-info/entry_points.txt
KB4IT-0.7.8.dist-info/top_level.txt
KB4IT-0.7.8.dist-info/RECORD
