Metadata-Version: 2.1
Name: KB4IT
Version: 0.7.8
Summary: A static website generator based on Asciidoctor sources.
Home-page: https://github.com/t00m/KB4IT
Author: Tomás Vírseda
Author-email: tomasvirseda@gmail.com
License: GPL v3
Download-URL: https://github.com/t00m/KB4IT/archive/master.zip
Platform: any
Classifier: Development Status :: 4 - Beta
Classifier: Environment :: Console
Classifier: Environment :: Web Environment
Classifier: Intended Audience :: Developers
Classifier: Intended Audience :: Information Technology
Classifier: Intended Audience :: System Administrators
Classifier: Intended Audience :: Other Audience
Classifier: License :: OSI Approved :: GNU General Public License v3 or later (GPLv3+)
Classifier: Natural Language :: English
Classifier: Operating System :: POSIX :: Linux
Classifier: Programming Language :: Python :: 3
Classifier: Topic :: Documentation
Classifier: Topic :: Software Development :: Documentation
Classifier: Topic :: Utilities
Requires-Dist: mako
